iosock/__init__.py
iosock/exception.py
iosock/darwin/client.py
iosock/darwin/kqueueserver.py
iosock/linux/client.py
iosock/linux/epollserver.py
iosock/linux/relayserver.py
iosock-0.0.23.dist-info/METADATA
iosock-0.0.23.dist-info/WHEEL
iosock-0.0.23.dist-info/licenses/LICENSE
iosock-0.0.23.dist-info/RECORD
