Metadata-Version: 2.3
Name: iosock
Version: 0.0.23
Summary: Simple I/O Socket
Project-URL: Homepage, https://github.com/chorong8883/iosock
Author-email: Chor <chorong8883@gmail.com>
License-File: LICENSE
Keywords: epoll,iosock,kqueue,socket
Classifier: License :: OSI Approved :: MIT License
Classifier: Operating System :: POSIX :: Linux
Classifier: Programming Language :: Python :: 3.10
Requires-Python: >=3.10
